azure/__init__.py
azure/cli/__init__.py
azure/cli/command_modules/__init__.py
azure/cli/command_modules/configure/__init__.py
azure/cli/command_modules/configure/_consts.py
azure/cli/command_modules/configure/_help.py
azure/cli/command_modules/configure/_params.py
azure/cli/command_modules/configure/_utils.py
azure/cli/command_modules/configure/commands.py
azure/cli/command_modules/configure/custom.py
azure_cli_configure-2.0.24.dist-info/METADATA
azure_cli_configure-2.0.24.dist-info/WHEEL
azure_cli_configure-2.0.24.dist-info/top_level.txt
azure_cli_configure-2.0.24.dist-info/RECORD
